mufzk_quantum/__init__.py
mufzk_quantum/circuit_analyzer.py
mufzk_quantum/graph.py
mufzk_quantum/oracles.py
mufzk_quantum/quantum.py
mufzk_quantum/utils.py
mufzk_quantum/visualization.py
mufzk_quantum-0.0.1.dist-info/METADATA
mufzk_quantum-0.0.1.dist-info/WHEEL
mufzk_quantum-0.0.1.dist-info/top_level.txt
mufzk_quantum-0.0.1.dist-info/RECORD
