Metadata-Version: 2.4
Name: mufzk_quantum
Version: 0.0.1
Author: Saba Arife Bozpolat
Author-email: saba.bozpolat@gmail.com
Requires-Dist: numpy<=2.0
Requires-Dist: scipy>=1.13.1
Requires-Dist: networkx>=3.4
Requires-Dist: matplotlib>=3.10
Dynamic: author
Dynamic: author-email
Dynamic: requires-dist
